xinet/__init__.py
xinet/image_utils.py
xinet/param.py
xinet/run_qt.py
xinet/Qt/__init__.py
xinet/Qt/qt5.py
xinet/Qt/qt6.py
xinet/Qt/utils/__init__.py
xinet/Qt/widgets/__init__.py
xinet/Qt/widgets/rect.py
xinet/Tk/__init__.py
xinet/Tk/utils/__init__.py
xinet/Tk/widgets/__init__.py
xinet/tkinterx/__init__.py
xinet/tkinterx/graph/__init__.py
xinet/tkinterx/graph/canvas.py
xinet/tkinterx/graph/draw.py
xinet/tkinterx/graph/shape.py
xinet-0.0.9.dist-info/LICENSE
xinet-0.0.9.dist-info/METADATA
xinet-0.0.9.dist-info/WHEEL
xinet-0.0.9.dist-info/top_level.txt
xinet-0.0.9.dist-info/RECORD
